{
  "schema_version": 1,
  "updated_at": "2026-06-12T22:10:36Z",
  "exploit": {
    "50-60": {
      "resolved_n": 0,
      "brier": null,
      "hit_rate": null,
      "adjustment": 0.0,
      "status": "collect"
    },
    "60-70": {
      "resolved_n": 0,
      "brier": null,
      "hit_rate": null,
      "adjustment": 0.0,
      "status": "collect"
    },
    "70-80": {
      "resolved_n": 0,
      "brier": null,
      "hit_rate": null,
      "adjustment": 0.0,
      "status": "collect"
    },
    "80-90": {
      "resolved_n": 0,
      "brier": null,
      "hit_rate": null,
      "adjustment": 0.0,
      "status": "collect"
    },
    "10-20": {
      "resolved_n": 1,
      "brier": 0.0324,
      "hit_rate": 0.0,
      "adjustment": 0.0,
      "status": "collect"
    },
    "20-30": {
      "resolved_n": 1,
      "brier": 0.0484,
      "hit_rate": 0.0,
      "adjustment": 0.0,
      "status": "collect"
    },
    "40-50": {
      "resolved_n": 2,
      "brier": 0.2025,
      "hit_rate": 0.0,
      "adjustment": 0.0,
      "status": "collect"
    }
  },
  "explore": {
    "30-40": {
      "resolved_n": 0,
      "brier_explore": null,
      "brier_market_p": null,
      "calibration_slope": null,
      "status": "collect"
    },
    "40-50": {
      "resolved_n": 3,
      "brier_explore": 0.206017,
      "brier_market_p": 0.19235,
      "calibration_slope": 0.0,
      "status": "collect"
    },
    "50-60": {
      "resolved_n": 0,
      "brier_explore": null,
      "brier_market_p": null,
      "calibration_slope": null,
      "status": "collect"
    },
    "60-70": {
      "resolved_n": 0,
      "brier_explore": null,
      "brier_market_p": null,
      "calibration_slope": null,
      "status": "collect"
    },
    "70-80": {
      "resolved_n": 0,
      "brier_explore": null,
      "brier_market_p": null,
      "calibration_slope": null,
      "status": "collect"
    },
    "0-10": {
      "resolved_n": 4,
      "brier_explore": 0.001686,
      "brier_market_p": 0.002791,
      "calibration_slope": 0.0,
      "status": "collect"
    }
  }
}
